mfd_switchmanagement/__init__.py
mfd_switchmanagement/base.py
mfd_switchmanagement/data_structures.py
mfd_switchmanagement/exceptions.py
mfd_switchmanagement/connections/__init__.py
mfd_switchmanagement/connections/api.py
mfd_switchmanagement/connections/base.py
mfd_switchmanagement/connections/ssh.py
mfd_switchmanagement/connections/vendors/__init__.py
mfd_switchmanagement/connections/vendors/cisco_api.py
mfd_switchmanagement/utils/__init__.py
mfd_switchmanagement/utils/match.py
mfd_switchmanagement/vendors/__init__.py
mfd_switchmanagement/vendors/arista/__init__.py
mfd_switchmanagement/vendors/arista/arista_7050.py
mfd_switchmanagement/vendors/arista/base.py
mfd_switchmanagement/vendors/brocade/__init__.py
mfd_switchmanagement/vendors/brocade/base.py
mfd_switchmanagement/vendors/cisco/__init__.py
mfd_switchmanagement/vendors/cisco/base.py
mfd_switchmanagement/vendors/cisco/os_4000.py
mfd_switchmanagement/vendors/cisco/os_6500.py
mfd_switchmanagement/vendors/cisco/nx_os/__init__.py
mfd_switchmanagement/vendors/cisco/nx_os/base.py
mfd_switchmanagement/vendors/dell/__init__.py
mfd_switchmanagement/vendors/dell/dell_os10/__init__.py
mfd_switchmanagement/vendors/dell/dell_os10/base.py
mfd_switchmanagement/vendors/dell/dell_os9/__init__.py
mfd_switchmanagement/vendors/dell/dell_os9/base.py
mfd_switchmanagement/vendors/dell/dell_os9/dell_7000.py
mfd_switchmanagement/vendors/dell/dell_os9/dell_8132.py
mfd_switchmanagement/vendors/dell/dell_os9/dell_force10.py
mfd_switchmanagement/vendors/dell/dell_os9/dell_s4128.py
mfd_switchmanagement/vendors/dell/dell_os9/dell_s5048.py
mfd_switchmanagement/vendors/extreme/__init__.py
mfd_switchmanagement/vendors/extreme/base.py
mfd_switchmanagement/vendors/extreme/extreme_exos.py
mfd_switchmanagement/vendors/ibm/__init__.py
mfd_switchmanagement/vendors/ibm/base.py
mfd_switchmanagement/vendors/junos/__init__.py
mfd_switchmanagement/vendors/junos/base.py
mfd_switchmanagement/vendors/mellanox/__init__.py
mfd_switchmanagement-2.19.0.dist-info/licenses/AUTHORS.md
mfd_switchmanagement-2.19.0.dist-info/licenses/LICENSE.md
mfd_switchmanagement-2.19.0.dist-info/METADATA
mfd_switchmanagement-2.19.0.dist-info/WHEEL
mfd_switchmanagement-2.19.0.dist-info/top_level.txt
mfd_switchmanagement-2.19.0.dist-info/RECORD
