Metadata-Version: 2.4
Name: mfd-switchmanagement
Version: 2.19.0
Summary: Module for handling operations on switches from different vendors (for example IBM, Cisco, Dell)
Project-URL: Homepage, https://github.com/intel/mfd
Project-URL: Repository, https://github.com/intel/mfd-switchmanagement
Project-URL: Issues, https://github.com/intel/mfd-switchmanagement/issues
Project-URL: Changelog, https://github.com/intel/mfd-switchmanagement/blob/main/CHANGELOG.md
Requires-Python: <3.14,>=3.10
License-File: LICENSE.md
License-File: AUTHORS.md
Requires-Dist: requests<3,>=2.27.0
Requires-Dist: netmiko>=4.6.0
Requires-Dist: mfd-common-libs>=1.11.0
Dynamic: license-file
